setup.cfg
setup.py
recsyscell/CellAutomatBinary.py
recsyscell/CellAutomatRegression.py
recsyscell/__init__.py
recsyscell.egg-info/PKG-INFO
recsyscell.egg-info/SOURCES.txt
recsyscell.egg-info/dependency_links.txt
recsyscell.egg-info/requires.txt
recsyscell.egg-info/top_level.txt