Metadata-Version: 2.1
Name: recsyscell
Version: 0.1.1
Summary: Binary and Regression task for simply collaboration filtering recommendation systems
Home-page: https://github.com/RyzhkovIlya/Cellular-automaton
Author-email: ryzhkov.ilya17@gmail.com
License: Apache License, Version 2.0, see LICENSE file
Download-URL: https://github.com/RyzhkovIlya/Cellular-automaton/blob/main/Cell_automat.version0.1.1.zip
Platform: UNKNOWN
